c_log/__init__.py
c_log/config.py
c_log/main.py
c_log-0.0.3.dist-info/METADATA
c_log-0.0.3.dist-info/WHEEL
c_log-0.0.3.dist-info/top_level.txt
c_log-0.0.3.dist-info/RECORD
