Metadata-Version: 2.1
Name: c-log
Version: 0.0.3
Summary: Colored logger
Home-page: UNKNOWN
Author: Andrey Bolshakov
Author-email: andrey.bolshakov@accenture.com
License: UNKNOWN
Platform: UNKNOWN
Classifier: Programming Language :: Python :: 3.8
Requires-Python: >=3.8
